Metadata-Version: 1.1
Name: urlfetch
Version: 0.5.7
Summary: An easy to use HTTP client
Home-page: https://github.com/ifduyue/urlfetch
Author: Yue Du
Author-email: ifduyue@gmail.com
License: BSD
Keywords: httpclient urlfetch
Platform: UNKNOWN
Classifier: Development Status :: 4 - Beta
Classifier: Programming Language :: Python
Classifier: Programming Language :: Python :: 3
Classifier: Intended Audience :: Developers
Classifier: License :: OSI Approved :: BSD License
Classifier: Operating System :: POSIX
Classifier: Operating System :: POSIX :: Linux
Classifier: Topic :: Internet :: WWW/HTTP
Classifier: Topic :: Software Development :: Libraries :: Python Modules
